{"trash_id":"edb1c0b89b0d129c6fba3a4ab667a2ee","trash_scores":{"default":1200},"name":"Sonarr Anime Seadex-99629-Alt","includeCustomFormatWhenRenaming":false,"specifications":[{"name":"Titles","implementation":"ReleaseTitleSpecification","negate":false,"required":true,"fields":{"value":"\\b(Angels of Death|殺戮の天使|Satsuriku no Tenshi|Angel of Massacre|Angel Slaughter|ทูตสวรรค์ทัณฑ์อำมหิต)\\b"}},{"name":"Encoders","implementation":"ReleaseTitleSpecification","negate":false,"required":true,"fields":{"value":"\\b(Aoba_xu|Aoba_xu)\\b"}}]}
