{"trash_id":"f6616b6785f1ab71cf103a585f6009d5","trash_scores":{"default":1800},"name":"Sonarr Anime Seadex-10681-Best","includeCustomFormatWhenRenaming":false,"specifications":[{"name":"Titles","implementation":"ReleaseTitleSpecification","negate":false,"required":true,"fields":{"value":"\\b(BLOOD-C: The Last Dark|劇場版 BLOOD-C The Last Dark|BLOOD-C: The Last Dark|Blood-C Movie)\\b"}},{"name":"Encoders","implementation":"ReleaseTitleSpecification","negate":false,"required":true,"fields":{"value":"\\b(TRiToN|TRiToN)\\b"}}]}
