{"trash_id":"a1a1d8f71b1f466b4a5f00543811c4b8","trash_scores":{"default":1200},"name":"Sonarr Anime Seadex-97907-Alt","includeCustomFormatWhenRenaming":false,"specifications":[{"name":"Titles","implementation":"ReleaseTitleSpecification","negate":false,"required":true,"fields":{"value":"\\b(Death March to the Parallel World Rhapsody|デスマーチからはじまる異世界狂想曲|Death March Kara Hajimaru Isekai Kyousoukyoku|โศกนาฏกรรมต่างโลกเริ่มต้นจากเดธมาร์ช|Pawai Maut Berujung Rapsodi Dunia Lain)\\b"}},{"name":"Encoders","implementation":"ReleaseTitleSpecification","negate":false,"required":true,"fields":{"value":"\\b(YURASUKA|YURASUKA)\\b"}}]}
