{"trash_id":"e78ec306441d877b86a31888fc55b211","trash_scores":{"default":1200},"name":"Sonarr Anime Seadex-113864-Alt","includeCustomFormatWhenRenaming":false,"specifications":[{"name":"Titles","implementation":"ReleaseTitleSpecification","negate":false,"required":true,"fields":{"value":"\\b(Special Crime Investigation Unit - Special 7 OVA|警視庁 特務部 特殊凶悪犯対策室 第七課 -トクナナ- OVA File\\.0\\.5「一年前、二条クジャクの憂い」|Keishicho Tokumu-bu Tokushu Kyoaku-han Taisaku-Shitsu Dai-Nana-ka: Tokunana OVA File 0\\.5|Special Crime Investigation Unit - Special 7 Episode 0\\.5|Special Crime Investigation Unit - Special 7 Episode OVA)\\b"}},{"name":"Encoders","implementation":"ReleaseTitleSpecification","negate":false,"required":true,"fields":{"value":"\\b(NOGRP|NOGRP)\\b"}}]}
