{"trash_id":"452d42d525be5300acc0779f5d751941","trash_scores":{"default":1800},"name":"Sonarr Anime Seadex-4654-Best","includeCustomFormatWhenRenaming":false,"specifications":[{"name":"Titles","implementation":"ReleaseTitleSpecification","negate":false,"required":true,"fields":{"value":"\\b(A Certain Magical Index|とある魔術の禁書目録|Toaru Majutsu no Index|Toaru Majutsu no Kinsho Mokuroku|אינדקס הקסומה|魔法禁书目录|فهرس السحر|อินเดกซ์คัมภีร์คาถาต้องห้าม|Cấm thư ma thuật Index|Μία Κάποια Μαγική Καλόγρια)\\b"}},{"name":"Encoders","implementation":"ReleaseTitleSpecification","negate":false,"required":true,"fields":{"value":"\\b(YURI|YURI)\\b"}}]}
