{"trash_id":"a4d84debd9fc1ce537b7f82a7d79b6f5","trash_scores":{"default":1800},"name":"Sonarr Anime Seadex-21733-Best","includeCustomFormatWhenRenaming":false,"specifications":[{"name":"Titles","implementation":"ReleaseTitleSpecification","negate":false,"required":true,"fields":{"value":"\\b(Descending Stories: Showa Genroku Rakugo Shinju|昭和元禄落語心中～助六再び篇～|Shouwa Genroku Rakugo Shinjuu: Sukeroku Futatabi-hen|Le Rakugo ou la vie 2|Shouwa Genroku Rakugo Shinjuu 2nd Season)\\b"}},{"name":"Encoders","implementation":"ReleaseTitleSpecification","negate":false,"required":true,"fields":{"value":"\\b(sam|sam)\\b"}}]}
