{"trash_id":"54d07c40aebed895df670ef4867a4147","trash_scores":{"default":1800},"name":"Sonarr Anime Seadex-101167-Best","includeCustomFormatWhenRenaming":false,"specifications":[{"name":"Titles","implementation":"ReleaseTitleSpecification","negate":false,"required":true,"fields":{"value":"\\b(Is It Wrong to Try to Pick Up Girls in a Dungeon\\? II|ダンジョンに出会いを求めるのは間違っているだろうかⅡ|Dungeon ni Deai wo Motomeru no wa Machigatteiru Darou ka II|Danmachi II|ダンジョンに出会いを求めるのは間違っているだろうか2|Dungeon ni Deai wo Motomeru no wa Machigatteiru Darou ka 2|Dungeon ni Deai o Motomeru no wa Machigatte Iru Darouka: Familia Myth II|มันผิดรึไงถ้าใจอยากจะพบรักในดันเจี้ยน ภาค 2|ダンまちⅡ)\\b"}},{"name":"Encoders","implementation":"ReleaseTitleSpecification","negate":false,"required":true,"fields":{"value":"\\b(sam|sam)\\b"}}]}
