{"trash_id":"a5f4af6369db76eeac64e74ad116c843","trash_scores":{"default":1200},"name":"Sonarr Anime Seadex-9751-Alt","includeCustomFormatWhenRenaming":false,"specifications":[{"name":"Titles","implementation":"ReleaseTitleSpecification","negate":false,"required":true,"fields":{"value":"\\b(Strike Witches: The Movie|ストライクウィッチーズ 劇場版|Strike Witches Movie|强袭魔女 剧场版)\\b"}},{"name":"Encoders","implementation":"ReleaseTitleSpecification","negate":false,"required":true,"fields":{"value":"\\b(Kametsu|Kametsu)\\b"}}]}
